[{"model": "api.knowledge", "pk": 301, "fields": {"knowledge_uuid": "e3029ae6-9976-4399-901e-57af97451957", "category": 10, "subcategory": 56, "type": 1}}, {"model": "api.knowledge", "pk": 302, "fields": {"knowledge_uuid": "bf78d45a-64fe-45e5-b776-d2feea55ec90", "category": 6, "subcategory": 28, "type": 1}}, {"model": "api.knowledge", "pk": 303, "fields": {"knowledge_uuid": "a612f053-ded1-4acb-ad4e-39ddcf1a7a55", "category": 10, "subcategory": 58, "type": 1}}, {"model": "api.knowledge", "pk": 304, "fields": {"knowledge_uuid": "12e1252d-ffa1-4c05-8423-305f114781e3", "category": 11, "subcategory": 63, "type": 1}}, {"model": "api.knowledge", "pk": 305, "fields": {"knowledge_uuid": "a1480ded-0251-414d-bae5-1cf921f7ad27", "category": 6, "subcategory": 28, "type": 1}}, {"model": "api.knowledge", "pk": 306, "fields": {"knowledge_uuid": "50ce640d-73d8-40b9-950e-b945f40ee60b", "category": 11, "subcategory": 63, "type": 1}}, {"model": "api.knowledge", "pk": 307, "fields": {"knowledge_uuid": "30d67bdf-418e-4f63-a830-4a498d8ed205", "category": 6, "subcategory": 29, "type": 1}}, {"model": "api.knowledge", "pk": 308, "fields": {"knowledge_uuid": "fa998d90-a86b-436f-99c4-e6692de6b279", "category": 10, "subcategory": 58, "type": 1}}, {"model": "api.knowledge", "pk": 309, "fields": {"knowledge_uuid": "99cb0848-29dd-4b75-b591-f6b335f10367", "category": 6, "subcategory": 36, "type": 1}}, {"model": "api.knowledge", "pk": 310, "fields": {"knowledge_uuid": "686ce761-e926-4d87-b47d-a472bcee1da2", "category": 6, "subcategory": 36, "type": 1}}, {"model": "api.knowledge", "pk": 311, "fields": {"knowledge_uuid": "57962456-5916-4e4d-9133-d7b9bd8ec92e", "category": 11, "subcategory": 63, "type": 1}}, {"model": "api.knowledge", "pk": 312, "fields": {"knowledge_uuid": "756118b4-783d-4ab2-b4f0-d18d9befc392", "category": 6, "subcategory": 36, "type": 1}}, {"model": "api.knowledge", "pk": 313, "fields": {"knowledge_uuid": "ff15bd52-f9b9-4a88-8f39-e62d2618ad07", "category": 6, "subcategory": 36, "type": 1}}, {"model": "api.knowledge", "pk": 314, "fields": {"knowledge_uuid": "6a7643f9-b9cf-435a-9398-b9d499a0b4a0", "category": 6, "subcategory": 36, "type": 1}}, {"model": "api.knowledge", "pk": 315, "fields": {"knowledge_uuid": "1e0f9e5a-17fa-469e-b775-46c53029c3bc", "category": 6, "subcategory": 36, "type": 1}}, {"model": "api.knowledge", "pk": 316, "fields": {"knowledge_uuid": "158ecbbd-7aec-4582-bc62-9fa67a6f6f69", "category": 11, "subcategory": 63, "type": 1}}, {"model": "api.knowledge", "pk": 317, "fields": {"knowledge_uuid": "378feeed-49fe-4c1d-92e8-81921caa33cf", "category": 6, "subcategory": 36, "type": 1}}, {"model": "api.knowledge", "pk": 318, "fields": {"knowledge_uuid": "cad18291-7aca-4d69-9270-8db0819b44bf", "category": 11, "subcategory": 63, "type": 1}}, {"model": "api.knowledge", "pk": 319, "fields": {"knowledge_uuid": "42b517f7-4d1f-4f21-9f00-f339b8ebcf22", "category": 4, "subcategory": 18, "type": 1}}, {"model": "api.knowledge", "pk": 320, "fields": {"knowledge_uuid": "f2dd9271-817d-4c30-b485-49f3faf2a0d3", "category": 6, "subcategory": 36, "type": 1}}, {"model": "api.knowledge", "pk": 321, "fields": {"knowledge_uuid": "1e3f1005-223c-4ef3-aa3c-1add2278691d", "category": 6, "subcategory": 36, "type": 1}}, {"model": "api.knowledge", "pk": 322, "fields": {"knowledge_uuid": "089a684c-18e6-4348-9a1b-5c16d52b9b32", "category": 6, "subcategory": 28, "type": 1}}, {"model": "api.knowledge", "pk": 323, "fields": {"knowledge_uuid": "c2927ee5-fd0d-4476-a9d1-0ffd2043999b", "category": 6, "subcategory": 37, "type": 1}}, {"model": "api.knowledge", "pk": 324, "fields": {"knowledge_uuid": "bf4f373f-7314-4259-9797-1791e6492b58", "category": 7, "subcategory": 43, "type": 1}}, {"model": "api.knowledge", "pk": 325, "fields": {"knowledge_uuid": "84986678-5c7c-4209-b319-1963d0ca3d8e", "category": 5, "subcategory": 22, "type": 1}}, {"model": "api.knowledge", "pk": 326, "fields": {"knowledge_uuid": "0b997a1a-f099-4be9-be55-94b240c98c3d", "category": 11, "subcategory": 63, "type": 1}}, {"model": "api.knowledge", "pk": 327, "fields": {"knowledge_uuid": "192fb04b-1fd8-460a-b1b7-14740545e101", "category": 6, "subcategory": 28, "type": 1}}, {"model": "api.knowledge", "pk": 328, "fields": {"knowledge_uuid": "dc221458-c69e-4771-b5da-ccebc501782d", "category": 5, "subcategory": 22, "type": 1}}, {"model": "api.knowledge", "pk": 329, "fields": {"knowledge_uuid": "fafd8bde-10e2-4fbe-8b12-3ef7af3d5a74", "category": 11, "subcategory": 63, "type": 1}}, {"model": "api.knowledge", "pk": 330, "fields": {"knowledge_uuid": "0dc567b0-9b4d-454d-8f41-8e944e47886c", "category": 10, "subcategory": 58, "type": 1}}, {"model": "api.knowledge", "pk": 331, "fields": {"knowledge_uuid": "447ad6fb-bef6-46fd-8021-c78dcc99655e", "category": 6, "subcategory": 28, "type": 1}}, {"model": "api.knowledge", "pk": 332, "fields": {"knowledge_uuid": "415a6856-2e09-42e6-8071-31994d8c8205", "category": 1, "subcategory": 2, "type": 1}}, {"model": "api.knowledge", "pk": 333, "fields": {"knowledge_uuid": "861d142b-c892-4089-a61c-79bc678379d1", "category": 10, "subcategory": 58, "type": 1}}, {"model": "api.knowledge", "pk": 334, "fields": {"knowledge_uuid": "1ca26914-0cf2-484b-8aab-4b3a4a5c777f", "category": 10, "subcategory": 58, "type": 1}}, {"model": "api.knowledge", "pk": 335, "fields": {"knowledge_uuid": "53875576-ce22-42da-bbe1-b72597614ce4", "category": 5, "subcategory": 22, "type": 1}}, {"model": "api.knowledge", "pk": 336, "fields": {"knowledge_uuid": "c586ed48-8179-46cb-b25d-82d13f6be9e8", "category": 5, "subcategory": 22, "type": 1}}, {"model": "api.knowledge", "pk": 337, "fields": {"knowledge_uuid": "e8ba911c-b276-4859-a944-31076207a341", "category": 5, "subcategory": 22, "type": 1}}, {"model": "api.knowledge", "pk": 338, "fields": {"knowledge_uuid": "3ef0d069-4bc5-4ab8-ae03-17db68db96c4", "category": 6, "subcategory": 37, "type": 1}}, {"model": "api.knowledge", "pk": 339, "fields": {"knowledge_uuid": "20895408-d588-43db-8ec2-90bbc427169c", "category": 11, "subcategory": 63, "type": 1}}, {"model": "api.knowledge", "pk": 340, "fields": {"knowledge_uuid": "feeddc1d-a422-4775-8092-4ecd8ed70527", "category": 11, "subcategory": 63, "type": 1}}, {"model": "api.knowledge", "pk": 341, "fields": {"knowledge_uuid": "ca77b7a0-0305-44e9-b107-9ec674978bc5", "category": 5, "subcategory": 22, "type": 1}}, {"model": "api.knowledge", "pk": 342, "fields": {"knowledge_uuid": "27573083-e356-4e99-a2b2-10bff37fbff3", "category": 11, "subcategory": 63, "type": 1}}, {"model": "api.knowledge", "pk": 343, "fields": {"knowledge_uuid": "4163d0f4-3534-45f5-8555-1576a11460e8", "category": 5, "subcategory": 22, "type": 1}}, {"model": "api.knowledge", "pk": 344, "fields": {"knowledge_uuid": "25ee6bdc-bf08-4c4f-b208-43f101973820", "category": 5, "subcategory": 22, "type": 1}}, {"model": "api.knowledge", "pk": 345, "fields": {"knowledge_uuid": "5c3611ae-9c0c-4e1e-8b07-dc011aadc593", "category": 5, "subcategory": 22, "type": 1}}, {"model": "api.knowledge", "pk": 346, "fields": {"knowledge_uuid": "92e2a4a6-6728-4aa7-b06d-2a01b939760e", "category": 6, "subcategory": 28, "type": 1}}, {"model": "api.knowledge", "pk": 347, "fields": {"knowledge_uuid": "2fbc8a89-b6c9-4826-ae6f-16d551b0ad5d", "category": 11, "subcategory": 63, "type": 1}}, {"model": "api.knowledge", "pk": 348, "fields": {"knowledge_uuid": "91fedf91-aab4-4764-afa6-ad83f4684119", "category": 6, "subcategory": 35, "type": 1}}, {"model": "api.knowledge", "pk": 349, "fields": {"knowledge_uuid": "e587a925-9ff2-4284-9dc7-5ef3c611d484", "category": 10, "subcategory": 58, "type": 1}}, {"model": "api.knowledge", "pk": 350, "fields": {"knowledge_uuid": "a6724a30-d757-44d6-8172-12f68d861ea1", "category": 10, "subcategory": 58, "type": 1}}, {"model": "api.knowledge", "pk": 351, "fields": {"knowledge_uuid": "b05e7e47-3715-407e-9510-bc511ba00e9c", "category": 10, "subcategory": 58, "type": 1}}, {"model": "api.knowledge", "pk": 352, "fields": {"knowledge_uuid": "0a9fb15b-df13-43da-b8f5-51a846a2d7aa", "category": 5, "subcategory": 22, "type": 1}}, {"model": "api.knowledge", "pk": 353, "fields": {"knowledge_uuid": "ccd3960d-a1c5-4af4-bc82-7c95ac556f36", "category": 6, "subcategory": 33, "type": 1}}, {"model": "api.knowledge", "pk": 354, "fields": {"knowledge_uuid": "07da2695-3c77-4899-a020-a522679c9538", "category": 5, "subcategory": 22, "type": 1}}, {"model": "api.knowledge", "pk": 355, "fields": {"knowledge_uuid": "ed4c2a15-3f96-4b2c-bbec-580e7385c1dd", "category": 5, "subcategory": 22, "type": 1}}, {"model": "api.knowledge", "pk": 356, "fields": {"knowledge_uuid": "5f2a305a-d762-4f82-9d1d-20e567302d05", "category": 6, "subcategory": 28, "type": 1}}, {"model": "api.knowledge", "pk": 357, "fields": {"knowledge_uuid": "da69b793-0146-4caa-ab0f-5eb1201919be", "category": 10, "subcategory": 58, "type": 1}}, {"model": "api.knowledge", "pk": 358, "fields": {"knowledge_uuid": "8b859fc7-c700-4667-a622-356dec53ea39", "category": 6, "subcategory": 31, "type": 1}}, {"model": "api.knowledge", "pk": 359, "fields": {"knowledge_uuid": "378a5be4-0dab-48c8-af35-65f10b043475", "category": 10, "subcategory": 56, "type": 1}}, {"model": "api.knowledge", "pk": 360, "fields": {"knowledge_uuid": "1f99bc16-127e-4eee-a61e-0e797eef9816", "category": 4, "subcategory": 15, "type": 1}}, {"model": "api.knowledge", "pk": 361, "fields": {"knowledge_uuid": "211c9a2c-6766-4ef9-ae74-c8342f473407", "category": 1, "subcategory": 2, "type": 1}}, {"model": "api.knowledge", "pk": 362, "fields": {"knowledge_uuid": "193284e9-3365-45b5-bc07-7fae4f18e168", "category": 6, "subcategory": 34, "type": 1}}, {"model": "api.knowledge", "pk": 363, "fields": {"knowledge_uuid": "0f4c789f-ea1b-4208-bd74-98f1a7de136e", "category": 6, "subcategory": 31, "type": 1}}, {"model": "api.knowledge", "pk": 364, "fields": {"knowledge_uuid": "3d57ca94-9874-47ea-9238-b4d833825f62", "category": 6, "subcategory": 30, "type": 1}}, {"model": "api.knowledge", "pk": 365, "fields": {"knowledge_uuid": "047ec5b3-a37f-4b6c-8295-a0af28803940", "category": 6, "subcategory": 35, "type": 1}}, {"model": "api.knowledge", "pk": 366, "fields": {"knowledge_uuid": "19c28ba7-3299-4657-99f6-5c4ae621ac34", "category": 10, "subcategory": 58, "type": 1}}, {"model": "api.knowledge", "pk": 367, "fields": {"knowledge_uuid": "2a2c5413-a498-4c20-b04f-ad3f4faf6177", "category": 9, "subcategory": 53, "type": 1}}, {"model": "api.knowledge", "pk": 368, "fields": {"knowledge_uuid": "0c56a92e-f3b7-4df9-9624-0babbbb20e3f", "category": 6, "subcategory": 32, "type": 1}}, {"model": "api.knowledge", "pk": 369, "fields": {"knowledge_uuid": "838e6f84-f38c-4e4f-8824-236192040e5b", "category": 7, "subcategory": 43, "type": 1}}, {"model": "api.knowledge", "pk": 370, "fields": {"knowledge_uuid": "117f77b2-7758-43c2-b7cc-8e4ef0c0b117", "category": 10, "subcategory": 56, "type": 1}}, {"model": "api.knowledge", "pk": 371, "fields": {"knowledge_uuid": "519b7724-2268-4348-9cf6-9b97abdff67d", "category": 6, "subcategory": 29, "type": 1}}, {"model": "api.knowledge", "pk": 372, "fields": {"knowledge_uuid": "8cbf4090-dad8-4d7f-b075-1190f9f6df71", "category": 10, "subcategory": 58, "type": 1}}, {"model": "api.knowledge", "pk": 373, "fields": {"knowledge_uuid": "6e0c1c20-6b5c-40b5-812d-f2608a9417a1", "category": 6, "subcategory": 27, "type": 1}}, {"model": "api.knowledge", "pk": 374, "fields": {"knowledge_uuid": "c15b4dc8-80d3-46ac-8d2b-9b889baf1ad1", "category": 4, "subcategory": 16, "type": 1}}, {"model": "api.knowledge", "pk": 375, "fields": {"knowledge_uuid": "ac7c8987-69a0-4bb3-ae32-89042e135128", "category": 10, "subcategory": 56, "type": 1}}, {"model": "api.knowledge", "pk": 376, "fields": {"knowledge_uuid": "9db4e915-495f-471f-850d-bfd7a286a32e", "category": 10, "subcategory": 58, "type": 1}}, {"model": "api.knowledge", "pk": 377, "fields": {"knowledge_uuid": "55343903-5d71-485a-9489-9a8313d488c2", "category": 6, "subcategory": 26, "type": 1}}, {"model": "api.knowledge", "pk": 378, "fields": {"knowledge_uuid": "23d8f5b3-caba-4388-8045-1c8ed6d3f8bc", "category": 10, "subcategory": 57, "type": 1}}, {"model": "api.knowledge", "pk": 379, "fields": {"knowledge_uuid": "20f37e45-8f97-44d3-8bc1-2ccfd40fc5b1", "category": 6, "subcategory": 31, "type": 1}}, {"model": "api.knowledge", "pk": 380, "fields": {"knowledge_uuid": "a0bd41a8-50fc-419b-a68d-e8368f80790e", "category": 2, "subcategory": 5, "type": 1}}, {"model": "api.knowledge", "pk": 381, "fields": {"knowledge_uuid": "19e6d21c-6c29-4126-95ab-9ffbec7719dc", "category": 6, "subcategory": 31, "type": 1}}, {"model": "api.knowledge", "pk": 382, "fields": {"knowledge_uuid": "314ace9a-1b49-4e31-a81f-39588e952fad", "category": 4, "subcategory": 16, "type": 1}}, {"model": "api.knowledge", "pk": 383, "fields": {"knowledge_uuid": "7fc7fd29-3d9e-464e-83fe-796a45f9b359", "category": 7, "subcategory": 45, "type": 1}}, {"model": "api.knowledge", "pk": 384, "fields": {"knowledge_uuid": "fea51c86-36f0-407b-8be3-d534b1c626ca", "category": 6, "subcategory": 34, "type": 1}}, {"model": "api.knowledge", "pk": 385, "fields": {"knowledge_uuid": "5579731e-f1d9-4af0-950b-e1a175d4d9e8", "category": 6, "subcategory": 28, "type": 1}}, {"model": "api.knowledge", "pk": 386, "fields": {"knowledge_uuid": "d76c1bd2-90eb-43c0-ba42-4984d2facbed", "category": 6, "subcategory": 34, "type": 1}}, {"model": "api.knowledge", "pk": 387, "fields": {"knowledge_uuid": "850cfd3d-8951-4ab7-a8a5-c26676ec2213", "category": 11, "subcategory": 63, "type": 1}}, {"model": "api.knowledge", "pk": 388, "fields": {"knowledge_uuid": "af976f94-2807-407f-9e23-fb1235559f57", "category": 6, "subcategory": 35, "type": 1}}, {"model": "api.knowledge", "pk": 389, "fields": {"knowledge_uuid": "803006b5-31c9-43c0-8ffb-c3ff5ad5f865", "category": 6, "subcategory": 34, "type": 1}}, {"model": "api.knowledge", "pk": 390, "fields": {"knowledge_uuid": "10e25c1c-8cba-401e-8923-295f61e22d2f", "category": 10, "subcategory": 58, "type": 1}}, {"model": "api.knowledge", "pk": 391, "fields": {"knowledge_uuid": "45442b0b-d04a-493b-bf27-261506666a96", "category": 12, "subcategory": 67, "type": 1}}, {"model": "api.knowledge", "pk": 392, "fields": {"knowledge_uuid": "ef117685-17ad-49d7-b8c3-cf52a55d897c", "category": 6, "subcategory": 34, "type": 1}}, {"model": "api.knowledge", "pk": 393, "fields": {"knowledge_uuid": "92f607a6-cf2b-4f8b-a7d6-681a2071ca55", "category": 4, "subcategory": 16, "type": 1}}, {"model": "api.knowledge", "pk": 394, "fields": {"knowledge_uuid": "00acece4-d367-4db8-af36-3ab7c7902034", "category": 6, "subcategory": 31, "type": 1}}, {"model": "api.knowledge", "pk": 395, "fields": {"knowledge_uuid": "f4944ca8-cb01-45ea-a0f7-8df5d9d3a1f9", "category": 6, "subcategory": 31, "type": 1}}, {"model": "api.knowledge", "pk": 396, "fields": {"knowledge_uuid": "0b9a5075-3c7f-4064-a0fa-6bf144aa9dbc", "category": 9, "subcategory": 50, "type": 1}}, {"model": "api.knowledge", "pk": 397, "fields": {"knowledge_uuid": "49b010e4-99b6-4b0c-9ae8-7180ef2e2b47", "category": 6, "subcategory": 33, "type": 1}}, {"model": "api.knowledge", "pk": 398, "fields": {"knowledge_uuid": "cae27492-250c-4e28-a909-4342935769b6", "category": 6, "subcategory": 31, "type": 1}}, {"model": "api.knowledge", "pk": 399, "fields": {"knowledge_uuid": "92d61ab6-b414-4529-aad1-6b74c08c5de3", "category": 9, "subcategory": 52, "type": 1}}]